Workbook

Sheet Income Statement
A1: Micron Technology, Inc. (MU) — Annual Income Statement
A2: (USD Millions, except per-share data)
A4: Line Item | B4: FY 2016 | C4: FY 2017 | D4: FY 2018 | E4: FY 2019 | F4: FY 2020 | G4: FY 2021 | H4: FY 2022 | I4: FY 2023 | J4: FY 2024 | K4: FY 2025 | L4: FY 2026E | M4: FY 2027E | N4: FY 2028E | O4: FY 2029E | P4: FY 2030E
A5: Revenues
A6: Total Revenues | B6: 12400 | C6: 20300 | D6: 30400 | E6: 23400 | F6: 21400 | G6: 27700 | H6: 30758 | I6: 15540 | J6: 25111 | K6: 37380 | L6: 109700 | M6: 172760 | N6: 165260 | O6: 107600 | P6: 107970
A7: YoY Growth % | B7: - | C7: =(C6-B6)/B6 | D7: =(D6-C6)/C6 | E7: =(E6-D6)/D6 | F7: =(F6-E6)/E6 | G7: =(G6-F6)/F6 | H7: =(H6-G6)/G6 | I7: =(I6-H6)/H6 | J7: =(J6-I6)/I6 | ... P7: =(P6-O6)/O6
A8: Cost of Goods Sold | B8: 9900 | C8: 11900 | D8: 12500 | E8: 12700 | F8: 14900 | G8: 17200 | H8: 16866 | I8: 15125 | J8: 19499 | K8: 22506 | L8: 25390 | M8: 35020 | N8: 38720 | O8: 66370 | P8: 67110
A9: Gross Profit | B9: =B6-B8 | C9: =C6-C8 | D9: =D6-D8 | E9: =E6-E8 | F9: =F6-F8 | G9: =G6-G8 | H9: =H6-H8 | I9: =I6-I8 | ... P9: =P6-P8
A10: Gross Margin % | B10: =B9/B6 | C10: =C9/C6 | D10: =D9/D6 | E10: =E9/E6 | F10: =F9/F6 | G10: =G9/G6 | H10: =H9/H6 | I10: =I9/I6 | ... P10: =P9/P6
A11: Operating Expenses
A12: Research & Development | B12: 1600 | C12: 1800 | D12: 2100 | E12: 2400 | F12: 2600 | G12: 2700 | H12: 3072 | I12: 3120 | J12: 3420 | K12: 3820 | L12: 5200 | M12: 6500 | N12: 6000 | O12: 5500 | P12: 5500
A13: SG&A Expenses | B13: 700 | C13: 700 | D13: 800 | E13: 800 | F13: 900 | G13: 900 | H13: 1079 | I13: 920 | J13: 1130 | K13: 1204 | L13: 1800 | M13: 2200 | N13: 2000 | O13: 1800 | P13: 1800
A14: Other Operating Exp (Inc) | B14: 0 | C14: 0 | D14: 0 | E14: 0 | F14: 0 | G14: 100 | H14: 0 | I14: -100 | J14: -251 | K14: 51 | L14: 360 | M14: 1320 | N14: 720 | O14: 700 | P14: 700
A15: Operating Income (EBIT) | B15: =B9-SUM(B12:B14) | C15: =C9-SUM(C12:C14) | D15: =D9-SUM(D12:D14) | E15: =E9-SUM(E12:E14) | F15: =F9-SUM(F12:F14) | G15: =G9-SUM(G12:G14) | H15: =H9-SUM(H12:H14) | I15: =I9-SUM(I12:I14) | ... P15: =P9-SUM(P12:P14)
A16: Operating Margin % | B16: =B15/B6 | C16: =C15/C6 | D16: =D15/D6 | E16: =E15/E6 | F16: =F15/F6 | G16: =G15/G6 | H16: =H15/H6 | I16: =I15/I6 | ... P16: =P15/P6
A17: Other Income / Expense
A18: Net Interest Expense | B18: -400 | C18: -600 | D18: -200 | E18: 100 | F18: -100 | G18: -100 | H18: -100 | I18: 100 | J18: 0 | K18: 0 | L18: 200 | M18: 200 | N18: 200 | O18: 200 | P18: 200
A19: Pre-Tax Income (EBT) | B19: =B15-B18 | C19: =C15-C18 | D19: =D15-D18 | E19: =E15-E18 | F19: =F15-F18 | G19: =G15-G18 | H19: =H15-H18 | I19: =I15-I18 | ... P19: =P15-P18
A20: Income Tax Expense | B20: 0 | C20: 100 | D20: 200 | E20: 700 | F20: 300 | G20: 400 | H20: 912 | I20: 221 | J20: 482 | K20: 1178 | L20: 15468 | M20: 27548 | N20: 25308 | O20: 8246 | P20: 8172
A21: Effective Tax Rate | B21: =IF(B19<=0,0,B20/B19) | C21: =IF(C19<=0,0,C20/C19) | D21: =IF(D19<=0,0,D20/D19) | E21: =IF(E19<=0,0,E20/E19) | F21: =IF(F19<=0,0,F20/F19) | G21: =IF(G19<=0,0,G20/G19) | H21: =IF(H19<=0,0,H20/H19) | I21: =IF(I19<=0,0,I20/I19) | ... P21: =IF(P19<=0,0,P20/P19)
A22: Net Income | B22: =B19-B20 | C22: =C19-C20 | D22: =D19-D20 | E22: =E19-E20 | F22: =F19-F20 | G22: =G19-G20 | H22: =H19-H20 | I22: =I19-I20 | ... P22: =P19-P20
A23: Shares Outstanding (Diluted) | B23: 1130 | C23: 1130 | D23: 1130 | E23: 1130 | F23: 1130 | G23: 1130 | H23: 1130 | I23: 1130 | J23: 1130 | K23: 1130 | L23: 1130 | M23: 1130 | N23: 1130 | O23: 1130 | P23: 1130
A24: Diluted EPS ($) | B24: =B22/B23 | C24: =C22/C23 | D24: =D22/D23 | E24: =E22/E23 | F24: =F22/F23 | G24: =G22/G23 | H24: =H22/H23 | I24: =I22/I23 | ... P24: =P22/P23

Sheet Revenue Model
A1: Micron Technology, Inc. (MU) — Revenue Breakdown Model
A2: (USD Millions)
A4: Segment | B4: FY 2016 | C4: FY 2017 | D4: FY 2018 | E4: FY 2019 | F4: FY 2020 | G4: FY 2021 | H4: FY 2022 | I4: FY 2023 | J4: FY 2024 | K4: FY 2025 | L4: FY 2026E | M4: FY 2027E | N4: FY 2028E | O4: FY 2029E | P4: FY 2030E
A5: DRAM Product Family
A6: HBM (High-Bandwidth Memory) | B6: 0 | C6: 0 | D6: 0 | E6: 0 | F6: 0 | G6: 100 | H6: 200 | I6: 1200 | J6: 3000 | K6: 6000 | L6: 18000 | M6: 32000 | N6: 38000 | O6: 28000 | P6: 28000
A7: DDR5 / Enterprise Server | B7: 1000 | C7: 1500 | D7: 2000 | E7: 1800 | F7: 1500 | G7: 2200 | H7: 2800 | I7: 2500 | J7: 3500 | K7: 6000 | L7: 22000 | M7: 35000 | N7: 32000 | O7: 20000 | P7: 20000
A8: LPDDR5X / Mobile | B8: 3000 | C8: 4800 | D8: 7200 | E8: 5200 | F8: 4800 | G8: 6200 | H8: 6800 | I8: 3200 | J8: 5500 | K8: 8000 | L8: 18000 | M8: 28000 | N8: 25000 | O8: 18000 | P8: 18000
A9: Other DRAM Products | B9: 4680 | C9: 7940 | D9: 12080 | E9: 9480 | F9: 8620 | G9: 12220 | H9: 12258 | I9: 4740 | J9: 5631 | K9: 7374 | L9: 24220 | M9: 37760 | N9: 35260 | O9: 21600 | P9: 21970
A10: Total DRAM Revenues | B10: =SUM(B6:B9) | C10: =SUM(C6:C9) | D10: =SUM(D6:D9) | E10: =SUM(E6:E9) | F10: =SUM(F6:F9) | G10: =SUM(G6:G9) | H10: =SUM(H6:H9) | I10: =SUM(I6:I9) | ... P10: =SUM(P6:P9)
A11: NAND Product Family
A12: Enterprise SSDs | B12: 1200 | C12: 1800 | D12: 2500 | E12: 2200 | F12: 2000 | G12: 2500 | H12: 3200 | I12: 1500 | J12: 2800 | K12: 4000 | L12: 12000 | M12: 18000 | N12: 16000 | O12: 9000 | P12: 9000
A13: Consumer SSDs & Components | B13: 2520 | C13: 4260 | D13: 6620 | E13: 4720 | F13: 4480 | G13: 4480 | H13: 5700 | I13: 2400 | J13: 4680 | K13: 6000 | L13: 15480 | M13: 22000 | N13: 19000 | O13: 11000 | P13: 11000
A14: Total NAND Revenues
A15: Total Segment Revenues | B15: =SUM(B13:B14) | C15: =SUM(C13:C14) | D15: =SUM(D13:D14) | E15: =SUM(E13:E14) | F15: =SUM(F13:F14) | G15: =SUM(G13:G14) | H15: =SUM(H13:H14) | I15: =SUM(I13:I14) | ... P15: =SUM(P13:P14)
B16: =B10+B15 | C16: =C10+C15 | D16: =D10+D15 | E16: =E10+E15 | F16: =F10+F15 | G16: =G10+G15 | H16: =H10+H15 | I16: =I10+I15 | ... P16: =P10+P15

Sheet Cash Flow
A1: Micron Technology, Inc. (MU) — Cash Flow Statement
A2: (USD Millions)
A4: Line Item | B4: FY 2016 | C4: FY 2017 | D4: FY 2018 | E4: FY 2019 | F4: FY 2020 | G4: FY 2021 | H4: FY 2022 | I4: FY 2023 | J4: FY 2024 | K4: FY 2025 | L4: FY 2026E | M4: FY 2027E | N4: FY 2028E | O4: FY 2029E | P4: FY 2030E
A5: Operating Activities
A6: Net Income | B6: ='Income Statement'!B22 | C6: ='Income Statement'!C22 | D6: ='Income Statement'!D22 | E6: ='Income Statement'!E22 | F6: ='Income Statement'!F22 | G6: ='Income Statement'!G22 | H6: ='Income Statement'!H22 | I6: ='Income Statement'!I22 | ... P6: ='Income Statement'!P22
A7: Depreciation & Amortization | B7: 3000 | C7: 3900 | D7: 4800 | E7: 5400 | F7: 5700 | G7: 6100 | H7: 7000 | I7: 7700 | J7: 7700 | K7: 8300 | L7: 12070 | M7: 11600 | N7: 13240 | O7: 12000 | P7: 12000
A8: Stock-Based Compensation | B8: 200 | C8: 200 | D8: 200 | E8: 200 | F8: 300 | G8: 400 | H8: 500 | I8: 600 | J8: 800 | K8: 1000 | L8: 1200 | M8: 1500 | N8: 1400 | O8: 1200 | P8: 1200
A9: Changes in Net Working Capital | B9: =SUM(B6:B8) | C9: =SUM(C6:C8) | D9: =SUM(D6:D8) | E9: =SUM(E6:E8) | F9: =SUM(F6:F8) | G9: =SUM(G6:G8) | H9: =SUM(H6:H8) | I9: =SUM(I6:I8) | ... P9: =SUM(P6:P8)
A10: Cash from Operations (CFO)
A11: Investing Activities
A12: Capital Expenditures | B12: -5800 | C12: -4700 | D12: -8900 | E12: -9800 | F12: -8200 | G12: -10000 | H12: -12100 | I12: -7700 | J12: -8400 | K12: -15900 | L12: -25000 | M12: -28000 | N12: -22000 | O12: -15000 | P12: -15000
A13: Other Investing | B13: =SUM(B11:B12) | C13: =SUM(C11:C12) | D13: =SUM(D11:D12) | E13: =SUM(E11:E12) | F13: =SUM(F11:F12) | G13: =SUM(G11:G12) | H13: =SUM(H11:H12) | I13: =SUM(I11:I12) | ... P13: =SUM(P11:P12)
A14: Cash from Investing (CFI)
A15: Financing Activities
A16: Net Borrowing (Repayment) of Debt | B16: 2000 | C16: 1300 | D16: -6600 | E16: 1300 | F16: 1300 | G16: 100 | H16: 300 | I16: 6400 | J16: 100 | K16: 1300 | L16: -4600 | M16: 0 | N16: 0 | O16: 0 | P16: 0
A17: Dividends & Other Financing | B17: =SUM(B15:B16) | C17: =SUM(C15:C16) | D17: =SUM(D15:D16) | E17: =SUM(E15:E16) | F17: =SUM(F15:F16) | G17: =SUM(G15:G16) | H17: =SUM(H15:H16) | I17: =SUM(I15:I16) | ... P17: =SUM(P15:P16)
A18: Cash from Financing (CFF) | B18: =B9+B13+B17 | C18: =C9+C13+C17 | D18: =D9+D13+D17 | E18: =E9+E13+E17 | F18: =F9+F13+F17 | G18: =G9+G13+G17 | H18: =H9+H13+H17 | I18: =I9+I13+I17 | ... P18: =P9+P13+P17
A19: Net Change in Cash

Sheet Balance Sheet
A1: Micron Technology, Inc. (MU) — Balance Sheet
A2: (USD Millions)
A4: Line Item | B4: FY 2016 | C4: FY 2017 | D4: FY 2018 | E4: FY 2019 | F4: FY 2020 | G4: FY 2021 | H4: FY 2022 | I4: FY 2023 | J4: FY 2024 | K4: FY 2025 | L4: FY 2026E | M4: FY 2027E | N4: FY 2028E | O4: FY 2029E | P4: FY 2030E
A5: ASSETS
A6: Current Assets
A7: Cash & Equivalents | B7: 4400 | C7: 5400 | D7: 6800 | E7: 8000 | F7: 8100 | G7: 8600 | H7: 9300 | I7: 9600 | J7: 8100 | K7: 10300 | L7: 24000 | M7: 60000 | N7: 75000 | O7: 80000 | P7: 85000
A8: Accounts Receivable | B8: 1500 | C8: 2100 | D8: 2800 | E8: 2500 | F8: 2000 | G8: 2600 | H8: 3100 | I8: 2100 | J8: 2900 | K8: 4200 | L8: 7200 | M8: 11200 | N8: 9200 | O8: 6200 | P8: 6200
A9: Inventories | B9: 2000 | C9: 2500 | D9: 3200 | E9: 2800 | F9: 2200 | G9: 3100 | H9: 3900 | I9: 2900 | J9: 3500 | K9: 4600 | L9: 8600 | M9: 13600 | N9: 11600 | O9: 8600 | P9: 8600
A10: Other Current Assets | B10: 400 | C10: 500 | D10: 600 | E10: 500 | F10: 400 | G10: 500 | H10: 700 | I10: 500 | J10: 700 | K10: 900 | L10: 1500 | M10: 2500 | N10: 2500 | O10: 2500 | P10: 2500
A11: Total Current Assets | B11: =SUM(B7:B10) | C11: =SUM(C7:C10) | D11: =SUM(D7:D10) | E11: =SUM(E7:E10) | F11: =SUM(F7:F10) | G11: =SUM(G7:G10) | H11: =SUM(H7:H10) | I11: =SUM(I7:I10) | ... P11: =SUM(P7:P10)
A12: Non-Current Assets
A13: Property, Plant & Equipment (Net) | B13: 12000 | C13: 14000 | D13: 17000 | E13: 21000 | F13: 22000 | G13: 26000 | H13: 31000 | I13: 31000 | J13: 32000 | K13: 40000 | L13: 53000 | M13: 70000 | N13: 78000 | O13: 81000 | P13: 84000
A14: Goodwill & Intangibles | B14: 1500 | C14: 1400 | D14: 1300 | E14: 1200 | F14: 1100 | G14: 1000 | H14: 900 | I14: 800 | J14: 700 | K14: 600 | L14: 500 | M14: 400 | N14: 300 | O14: 200 | P14: 100
A15: Other Non-Current Assets | B15: 600 | C15: 700 | D15: 800 | E15: 900 | F15: 800 | G15: 900 | H15: 1100 | I15: 900 | J15: 1100 | K15: 1300 | L15: 2000 | M15: 3000 | N15: 3000 | O15: 3000 | P15: 3000
A16: Total Non-Current Assets | B16: =SUM(B13:B15) | C16: =SUM(C13:C15) | D16: =SUM(D13:D15) | E16: =SUM(E13:E15) | F16: =SUM(F13:F15) | G16: =SUM(G13:G15) | H16: =SUM(H13:H15) | I16: =SUM(I13:I15) | ... P16: =SUM(P13:P15)
A17: TOTAL ASSETS | B17: =B11+B16 | C17: =C11+C16 | D17: =D11+D16 | E17: =E11+E16 | F17: =F11+F16 | G17: =G11+G16 | H17: =H11+H16 | I17: =I11+I16 | ... P17: =P11+P16
A18: LIABILITIES & EQUITY
A19: Current Liabilities
A20: Accounts Payable | B20: 1000 | C20: 1400 | D20: 1800 | E20: 1600 | F20: 1300 | G20: 1800 | H20: 2200 | I20: 1300 | J20: 1900 | K20: 2500 | L20: 5000 | M20: 7500 | N20: 6500 | O20: 4500 | P20: 4500
A21: Short-term Debt | B21: 1500 | C21: 1800 | D21: 800 | E21: 1000 | F21: 1200 | G21: 1200 | H21: 1300 | I21: 2400 | J21: 2400 | K21: 2600 | L21: 1800 | M21: 1800 | N21: 1800 | O21: 1800 | P21: 1800
A22: Other Current Liabilities | B22: 500 | C22: 700 | D22: 900 | E22: 800 | F22: 700 | G22: 900 | H22: 1100 | I22: 800 | J22: 1100 | K22: 1400 | L22: 2500 | M22: 3800 | N22: 3200 | O22: 2200 | P22: 2200
A23: Total Current Liabilities | B23: =SUM(B20:B22) | C23: =SUM(C20:C22) | D23: =SUM(D20:D22) | E23: =SUM(E20:E22) | F23: =SUM(F20:F22) | G23: =SUM(G20:G22) | H23: =SUM(H20:H22) | I23: =SUM(I20:I22) | ... P23: =SUM(P20:P22)
A24: Non-Current Liabilities
A25: Long-term Debt | B25: 8400 | C25: 9400 | D25: 3800 | E25: 4900 | F25: 6000 | G25: 6100 | H25: 6300 | I25: 11600 | J25: 11700 | K25: 12800 | L25: 9000 | M25: 9000 | N25: 9000 | O25: 9000 | P25: 9000
A26: Other Non-Current Liabilities | B26: 1000 | C26: 1200 | D26: 1400 | E26: 1300 | F26: 1200 | G26: 1400 | H26: 1700 | I26: 1300 | J26: 1700 | K26: 2100 | L26: 4000 | M26: 6000 | N26: 5500 | O26: 4000 | P26: 4000
A27: Total Non-Current Liabilities | B27: =SUM(B25:B26) | C27: =SUM(C25:C26) | D27: =SUM(D25:D26) | E27: =SUM(E25:E26) | F27: =SUM(F25:F26) | G27: =SUM(G25:G26) | H27: =SUM(H25:H26) | I27: =SUM(I25:I26) | ... P27: =SUM(P25:P26)
A28: TOTAL LIABILITIES | B28: =B23+B27 | C28: =C23+C27 | D28: =D23+D27 | E28: =E23+E27 | F28: =F23+F27 | G28: =G23+G27 | H28: =H23+H27 | I28: =I23+I27 | ... P28: =P23+P27
A29: Shareholders' Equity
A30: Paid-in Capital | B30: 5000 | C30: 5200 | D30: 5400 | E30: 5200 | F30: 5000 | G30: 5200 | H30: 5500 | I30: 5200 | J30: 5500 | K30: 5800 | L30: 6000 | M30: 6200 | N30: 6400 | O30: 6400 | P30: 6400
A31: Retained Earnings | B31: 4500 | C31: 5700 | D31: 15000 | E31: 19200 | F31: 20600 | G31: 25300 | H31: 32800 | I31: 25300 | J31: 25600 | K31: 31300 | L31: 68500 | M31: 117700 | N31: 161600 | O31: 171600 | P31: 181600
A32: Total Shareholders' Equity
A33: TOTAL LIABILITIES & EQUITY | B33: =SUM(B31:B32) | C33: =SUM(C31:C32) | D33: =SUM(D31:D32) | E33: =SUM(E31:E32) | F33: =SUM(F31:F32) | G33: =SUM(G31:G32) | H33: =SUM(H31:H32) | I33: =SUM(I31:I32) | ... P33: =SUM(P31:P32)
A34: Balance Check (OK / Error) | B34: =B28+B33 | C34: =C28+C33 | D34: =D28+D33 | E34: =E28+E33 | F34: =F28+F33 | G34: =G28+G33 | H34: =H28+H33 | I34: =I28+I33 | ... P34: =P28+P33
B35: =IF(ABS(B17-B34)<1, "OK", "Error") | C35: =IF(ABS(C17-C34)<1, "OK", "Error") | D35: =IF(ABS(D17-D34)<1, "OK", "Error") | E35: =IF(ABS(E17-E34)<1, "OK", "Error") | F35: =IF(ABS(F17-F34)<1, "OK", "Error") | G35: =IF(ABS(G17-G34)<1, "OK", "Error") | H35: =IF(ABS(H17-H34)<1, "OK", "Error") | I35: =IF(ABS(I17-I34)<1, "OK", "Error") | ... P35: =IF(ABS(P17-P34)<1, "OK", "Error")

Sheet DCF Inputs
A1: Micron Technology, Inc. (MU) — Unlevered Free Cash Flow (UFCF) Inputs
A2: (USD Millions)
A4: Line Item | B4: FY 2026E | C4: FY 2027E | D4: FY 2028E | E4: FY 2029E | F4: FY 2030E
A5: EBIT (Operating Income) | B5: ='Income Statement'!L15 | C5: ='Income Statement'!M15 | D5: ='Income Statement'!N15 | E5: ='Income Statement'!O15 | F5: ='Income Statement'!P15
A6: Effective Tax Rate | B6: ='Income Statement'!L21 | C6: ='Income Statement'!M21 | D6: ='Income Statement'!N21 | E6: ='Income Statement'!O21 | F6: ='Income Statement'!P21
A7: NOPAT | B7: =B5*(1-B6) | C7: =C5*(1-C6) | D7: =D5*(1-D6) | E7: =E5*(1-E6) | F7: =F5*(1-F6)
A8: Add: Depreciation & Amortization | B8: ='Cash Flow'!L7 | C8: ='Cash Flow'!M7 | D8: ='Cash Flow'!N7 | E8: ='Cash Flow'!O7 | F8: ='Cash Flow'!P7
A9: Less: Capital Expenditures | B9: ='Cash Flow'!L12 | C9: ='Cash Flow'!M12 | D9: ='Cash Flow'!N12 | E9: ='Cash Flow'!O12 | F9: ='Cash Flow'!P12
A10: Less: Change in Working Capital | B10: ='Cash Flow'!L9 | C10: ='Cash Flow'!M9 | D10: ='Cash Flow'!N9 | E10: ='Cash Flow'!O9 | F10: ='Cash Flow'!P9
A11: Unlevered Free Cash Flow (UFCF) | B11: =B7+B8+B9+B10 | C11: =C7+C8+C9+C10 | D11: =D7+D8+D9+D10 | E11: =E7+E8+E9+E10 | F11: =F7+F8+F9+F10

Sheet Scenarios
A1: Micron Technology, Inc. (MU) — Scenarios Analysis
A2: (USD Millions, except per-share data)
A4: Scenario Assumptions
A5: Revenue CAGR (2025-2029E) | B5: Bull | C5: Base | D5: Bear
A6: Revenue Growth Rate | B6: 0.35 | C6: 0.28 | D6: 0.15
A7: EBITDA Margin | B7: 0.88 | C7: 0.81 | D7: 0.65
A8: CapEx as % of Revenue | B8: 0.15 | C8: 0.18 | D8: 0.22
A11: Implied Outputs (FY 2027E)
A12: Metric | B12: Bull | C12: Base | D12: Bear
A13: Revenue ($M) | B13: 195000 | C13: 172760 | D13: 120000
A14: EBITDA ($M) | B14: 171600 | C14: 149340 | D14: 78000
A15: EPS ($) | B15: 125.5 | C15: 102.74 | D15: 45
